genPwd/__init__.py
genPwd/generate_password.py
genPwd/test_passw.py
genPwd-1.3.0.4.dist-info/METADATA
genPwd-1.3.0.4.dist-info/WHEEL
genPwd-1.3.0.4.dist-info/entry_points.txt
genPwd-1.3.0.4.dist-info/top_level.txt
genPwd-1.3.0.4.dist-info/RECORD
