Metadata-Version: 2.1
Name: genPwd
Version: 1.3.0.4
Summary: This is a sample Description
Home-page: https://github.com/kanchann/GenPwd
Author: Kanchan
Author-email: kanchanbora321@gmail.com
Classifier: Programming Language :: Python :: 3
Classifier: License :: OSI Approved :: MIT License
Classifier: Operating System :: OS Independent
